androguard/__init__.py
androguard/cli/__init__.py
androguard/cli/cli.py
androguard/cli/main.py
androguard/core/__init__.py
androguard/core/analysis/__init__.py
androguard/core/analysis/analysis.py
androguard/core/androconf.py
androguard/core/api_specific_resources/__init__.py
androguard/core/api_specific_resources/aosp_permissions/permissions_10.json
androguard/core/api_specific_resources/aosp_permissions/permissions_13.json
androguard/core/api_specific_resources/aosp_permissions/permissions_14.json
androguard/core/api_specific_resources/aosp_permissions/permissions_15.json
androguard/core/api_specific_resources/aosp_permissions/permissions_16.json
androguard/core/api_specific_resources/aosp_permissions/permissions_17.json
androguard/core/api_specific_resources/aosp_permissions/permissions_18.json
androguard/core/api_specific_resources/aosp_permissions/permissions_19.json
androguard/core/api_specific_resources/aosp_permissions/permissions_21.json
androguard/core/api_specific_resources/aosp_permissions/permissions_22.json
androguard/core/api_specific_resources/aosp_permissions/permissions_23.json
androguard/core/api_specific_resources/aosp_permissions/permissions_24.json
androguard/core/api_specific_resources/aosp_permissions/permissions_25.json
androguard/core/api_specific_resources/aosp_permissions/permissions_26.json
androguard/core/api_specific_resources/aosp_permissions/permissions_27.json
androguard/core/api_specific_resources/aosp_permissions/permissions_28.json
androguard/core/api_specific_resources/aosp_permissions/permissions_29.json
androguard/core/api_specific_resources/aosp_permissions/permissions_4.json
androguard/core/api_specific_resources/aosp_permissions/permissions_5.json
androguard/core/api_specific_resources/aosp_permissions/permissions_6.json
androguard/core/api_specific_resources/aosp_permissions/permissions_7.json
androguard/core/api_specific_resources/aosp_permissions/permissions_8.json
androguard_p-4.1.1.dist-info/METADATA
androguard_p-4.1.1.dist-info/WHEEL
androguard_p-4.1.1.dist-info/entry_points.txt
androguard_p-4.1.1.dist-info/RECORD
